ranking/__init__.py
ranking/fast_iteration.py
ranking/parsing.py
ranking/results.py
ranking/sampling.py
ranking/util.py
pairwise_ranking-1.0.2.dist-info/LICENSE
pairwise_ranking-1.0.2.dist-info/METADATA
pairwise_ranking-1.0.2.dist-info/WHEEL
pairwise_ranking-1.0.2.dist-info/top_level.txt
pairwise_ranking-1.0.2.dist-info/RECORD
