Metadata-Version: 2.1
Name: pairwise-ranking
Version: 1.0.2
Summary: Infer rankings and nature of hierarchies from paired comparisons
Author-email: Maximilian Jerdee <mjerdee@umich.edu>, Mark Newman <mejn@umich.edu>
License: Copyright (c) 2023 Maximilian Jerdee and Mark Newman
Project-URL: Homepage, https://github.com/maxjerdee/pairwise-ranking
Keywords: ranking,statistics,rating,bayesian
Classifier: License :: OSI Approved :: MIT License
Classifier: Programming Language :: Python
Classifier: Programming Language :: Python :: 3
Requires-Python: >=3.9
License-File: LICENSE
Requires-Dist: pystan >=3.7.0
Requires-Dist: matplotlib >=3.8.0
Requires-Dist: numpy >=1.26.0
Requires-Dist: scipy >=1.11.3
Requires-Dist: networkx ==3.2.1
Requires-Dist: pandas ==2.1.3
Provides-Extra: dev
Requires-Dist: black ; extra == 'dev'
Requires-Dist: bumpver ; extra == 'dev'
Requires-Dist: isort ; extra == 'dev'
Requires-Dist: pip-tools ; extra == 'dev'
Requires-Dist: pytest ; extra == 'dev'
